fake_doctors/__init__.py
fake_doctors/annotation.py
fake_doctors/dataset.py
fake_doctors/localization.py
fake_doctors/mask.py
fake_doctors/sampling.py
fake_doctors-0.0.5.2.dist-info/LICENSE
fake_doctors-0.0.5.2.dist-info/METADATA
fake_doctors-0.0.5.2.dist-info/WHEEL
fake_doctors-0.0.5.2.dist-info/top_level.txt
fake_doctors-0.0.5.2.dist-info/RECORD
