Metadata-Version: 2.1
Name: fake-doctors
Version: 0.0.5.2
Summary: Tools for handling whole slide image
Home-page: https://github.com/timecostslives/fake-doctors
Author: Kim Du Nam
Author-email: timecostslives@gmail.com
License: UNKNOWN
Platform: UNKNOWN
Classifier: Programming Language :: Python :: 3
Classifier: License :: OSI Approved :: MIT License
Classifier: Operating System :: POSIX :: Linux
Requires-Python: >=3.6
